{
    "@context": {
        "dcterms": "http://purl.org/dc/terms/",
        "edm": "http://www.europeana.eu/schemas/edm/",
        "foaf": "http://xmlns.com/foaf/0.1/",
        "htrc": "http://wcsa.htrc.illinois.edu/",
        "rdf": "http://www.w3.org/1999/02/22-rdf-syntax-ns#",
        "rdfs": "http://www.w3.org/2000/01/rdf-schema#",
        "xsd": "http://www.w3.org/2001/XMLSchema#",
        "ht": "https://www.hathitrust.org/",
        "prism": "http://prismstandard.org/namespaces/basic/2.0/",
        "astrs": "http://www.w3.org/ns/activitystreams#",
        "bf": "http://id.loc.gov/ontologies/bibframe/",
        "id": "@id",
        "type": "@type",
        "graph": "@graph",
        "WorksetPage": "htrc:WorksetPage",
        "Workset": "htrc:Workset",
        "briefDescription": "htrc:hasBriefDescription",
        "fullDescription": "htrc:hasFullDescription",
        "catalogDescription": "htrc:hasCatalogDescription",
        "gathers": "edm:gathers",
        "gatheredInto": "edm:isGatheredInto",
        "creator": "dcterms:creator",
        "criterion": "htrc:hasCriterion",
        "motivation": "htrc:hasResearchMotivation",
        "intent": "htrc:intendedForUse",
        "visibility": "htrc:hasVisibility",
        "group": "htrc:hasGroup",
        "mayUseWith": "htrc:mediatedBy",
        "extent": "dcterms:extent",
        "created": "dcterms:created",
        "publisher": "dcterms:publisher",
        "title": "dcterms:title",
        "description": "dcterms:abstract",
        "languages": "dcterms:language",
        "temporal": "dcterms:temporal",
        "formats": "dcterms:format",
        "origin": "ht:origin",
        "contributor": "dcterms:contributor",
        "subject": "dcterms:subject",
        "volume": "prism:volume",
        "accessRights": "dcterms:accessRights",
        "partOf": "dcterms:isPartOf",
        "versionOf": "dcterms:isVersionOf",
        "items": "astrs:items",
        "startIndex": "astrs:startIndex",
        "isPartOf": "astrs:partOf",
        "work": "bf:instanceOf",
        "altTitles": "htrc:AltTitles",
        "bibfTitle": "htrc:Title",
        "workGenre": "htrc:WorkGenre",
        "workTitle": "htrc:WorkTitle",
        "imprint": "htrc:imprint",
        "pubLocation": "htrc:pubLocation",
        "pubYear": "htrc:pubYear",
        "provisionActivity": "bf:provisionActivity"
    },
    "id": "https://worksets.hathitrust.org/wsid/34861c20-e287-11ed-8d53-d5e72103273f",
    "type": "Workset",
    "description": "Curated by José González with HathiTrust Research Center for the Mellon-Funded SCWAReD project.",
    "created": "2023-04-24",
    "creator": [
        "José Eduardo González"
    ],
    "contributor": [
        "Isabella Magni",
        "John A. Walsh",
        "J. Stephen Downie",
        "Maryemma Graham",
        "Yu “Marie” Ma",
        "Glen Layne-Worthey",
        "Ryan Dubnicek",
        "Janet Swatscheno"
    ],
    "extent": 46,
    "title": "Narcoliterature",
    "visibility": "public",
    "intent": {"id": "http://example.org/htrc.algorithm"},
    "gathers": [
        {"id": "http://hdl.handle.net/2027/txu.059173026647930"},
        {"id": "http://hdl.handle.net/2027/mdp.39015040572763"},
        {"id": "http://hdl.handle.net/2027/txu.059173032183561"},
        {"id": "http://hdl.handle.net/2027/ien.35556034377929"},
        {"id": "http://hdl.handle.net/2027/mdp.39015040067384"},
        {"id": "http://hdl.handle.net/2027/uc1.b3785042"},
        {"id": "http://hdl.handle.net/2027/txu.059173026646803"},
        {"id": "http://hdl.handle.net/2027/uc1.32106012535404"},
        {"id": "http://hdl.handle.net/2027/mdp.39015040068242"},
        {"id": "http://hdl.handle.net/2027/mdp.39015061205111"},
        {"id": "http://hdl.handle.net/2027/mdp.39015050804775"},
        {"id": "http://hdl.handle.net/2027/mdp.39015057028014"},
        {"id": "http://hdl.handle.net/2027/txu.059173032944293"},
        {"id": "http://hdl.handle.net/2027/mdp.39015061778067"},
        {"id": "http://hdl.handle.net/2027/txu.059173004317091"},
        {"id": "http://hdl.handle.net/2027/uc1.b3598462"},
        {"id": "http://hdl.handle.net/2027/wu.89083299057"},
        {"id": "http://hdl.handle.net/2027/txu.059173019056210"},
        {"id": "http://hdl.handle.net/2027/uc1.32106016211820"},
        {"id": "http://hdl.handle.net/2027/mdp.39015057579982"},
        {"id": "http://hdl.handle.net/2027/txu.059173000933050"},
        {"id": "http://hdl.handle.net/2027/mdp.39015063239233"},
        {"id": "http://hdl.handle.net/2027/txu.059173030605050"},
        {"id": "http://hdl.handle.net/2027/txu.059173001836897"},
        {"id": "http://hdl.handle.net/2027/uc1.b3722770"},
        {"id": "http://hdl.handle.net/2027/txu.059172132376178"},
        {"id": "http://hdl.handle.net/2027/uc1.b3776399"},
        {"id": "http://hdl.handle.net/2027/mdp.39015060049072"},
        {"id": "http://hdl.handle.net/2027/txu.059173005330029"},
        {"id": "http://hdl.handle.net/2027/inu.30000087824060"},
        {"id": "http://hdl.handle.net/2027/txu.059173015451507"},
        {"id": "http://hdl.handle.net/2027/wu.89052113339"},
        {"id": "http://hdl.handle.net/2027/mdp.39015061331362"},
        {"id": "http://hdl.handle.net/2027/mdp.39015054451763"},
        {"id": "http://hdl.handle.net/2027/mdp.39015062859577"},
        {"id": "http://hdl.handle.net/2027/txu.059173004983945"},
        {"id": "http://hdl.handle.net/2027/inu.30000093063380"},
        {"id": "http://hdl.handle.net/2027/txu.059173004256667"},
        {"id": "http://hdl.handle.net/2027/mdp.39015056814810"},
        {"id": "http://hdl.handle.net/2027/mdp.39015056430138"},
        {"id": "http://hdl.handle.net/2027/txu.059173017166261"},
        {"id": "http://hdl.handle.net/2027/uc1.b3784095"},
        {"id": "http://hdl.handle.net/2027/mdp.39015056163135"},
        {"id": "http://hdl.handle.net/2027/txu.059173006697903"},
        {"id": "http://hdl.handle.net/2027/txu.059173026649335"},
        {"id": "http://hdl.handle.net/2027/mdp.39015056205316"}
    ]
}